ofscraper/__main__.py
ofscraper/__version__.py
ofscraper/classes/labels.py
ofscraper/classes/placeholder.py
ofscraper/classes/of/base.py
ofscraper/classes/of/media.py
ofscraper/classes/of/models.py
ofscraper/classes/of/posts.py
ofscraper/classes/table/app.py
ofscraper/classes/table/compose.py
ofscraper/classes/table/const.py
ofscraper/classes/table/css.py
ofscraper/classes/table/fields/boolfield.py
ofscraper/classes/table/fields/datefield.py
ofscraper/classes/table/fields/downloadfield.py
ofscraper/classes/table/fields/mediafield.py
ofscraper/classes/table/fields/numfield.py
ofscraper/classes/table/fields/pricefield.py
ofscraper/classes/table/fields/responsefield.py
ofscraper/classes/table/fields/selectfield.py
ofscraper/classes/table/fields/sizefield.py
ofscraper/classes/table/fields/textsearch.py
ofscraper/classes/table/fields/timefield.py
ofscraper/classes/table/inputs/filterinput.py
ofscraper/classes/table/inputs/intergerinput.py
ofscraper/classes/table/inputs/strinput.py
ofscraper/classes/table/sections/sidebar.py
ofscraper/classes/table/sections/table.py
ofscraper/classes/table/sections/table_console.py
ofscraper/classes/table/utils/lock.py
ofscraper/classes/table/utils/names.py
ofscraper/commands/check.py
ofscraper/commands/db.py
ofscraper/commands/manual.py
ofscraper/commands/metadata/consumer.py
ofscraper/commands/metadata/desc.py
ofscraper/commands/metadata/manager.py
ofscraper/commands/metadata/metadata.py
ofscraper/commands/scraper/scraper.py
ofscraper/commands/scraper/actions/download/download.py
ofscraper/commands/scraper/actions/download/run.py
ofscraper/commands/scraper/actions/download/managers/alt_download.py
ofscraper/commands/scraper/actions/download/managers/downloadmanager.py
ofscraper/commands/scraper/actions/download/managers/main_download.py
ofscraper/commands/scraper/actions/download/utils/chunk.py
ofscraper/commands/scraper/actions/download/utils/desc.py
ofscraper/commands/scraper/actions/download/utils/ffmpeg.py
ofscraper-3.13.9.dist-info/METADATA
ofscraper-3.13.9.dist-info/WHEEL
ofscraper-3.13.9.dist-info/entry_points.txt
ofscraper-3.13.9.dist-info/licenses/LICENSE
ofscraper-3.13.9.dist-info/RECORD
