Metadata-Version: 2.4
Name: ofscraper
Version: 3.13.9
Summary: automatically scrape onlyfans
Project-URL: Homepage, https://github.com/datawhores/OF-Scraper
Author-email: datawhores <datawhores@riseup.net>
License-File: LICENSE
Requires-Python: <3.14,>=3.11
Requires-Dist: aiofiles~=23.2.1
Requires-Dist: aiolimiter~=1.1.0
Requires-Dist: aioprocessing~=2.0.1
Requires-Dist: aiosqlite~=0.20.0
Requires-Dist: arrow~=1.3.0
Requires-Dist: async-property~=0.2.2
Requires-Dist: browser-cookie3==0.19.1
Requires-Dist: bs4~=0.0.2
Requires-Dist: certifi~=2024.2.2
Requires-Dist: cloup~=3.0.5
Requires-Dist: dill~=0.3.8
Requires-Dist: diskcache~=5.6.3
Requires-Dist: dotenv>=0.9.9
Requires-Dist: faust-cchardet~=2.1.19
Requires-Dist: filelock~=3.13.1
Requires-Dist: httpx-aiohttp~=0.1.2
Requires-Dist: httpx-curl-cffi~=0.1.3
Requires-Dist: httpx[http2]~=0.28.1
Requires-Dist: humanfriendly~=10.0
Requires-Dist: idna==3.7
Requires-Dist: inquirerpy~=0.3.4
Requires-Dist: limiter~=0.5.0
Requires-Dist: lxml~=5.1.0
Requires-Dist: more-itertools~=10.2.0
Requires-Dist: mpegdash~=0.4.0
Requires-Dist: multiprocess~=0.70.16
Requires-Dist: pathvalidate~=3.2.0
Requires-Dist: prompt-toolkit~=3.0.43
Requires-Dist: psutil~=5.9.8
Requires-Dist: pycryptodome~=3.20.0
Requires-Dist: pynumparser~=1.4.1
Requires-Dist: pywidevine~=1.8.0
Requires-Dist: pyyaml>=6.0.2
Requires-Dist: requests~=2.31.0
Requires-Dist: rich~=13.7.1
Requires-Dist: schedule~=1.2.1
Requires-Dist: setproctitle~=1.3.3
Requires-Dist: speedtest-cli~=2.1.3
Requires-Dist: tenacity~=8.2.3
Requires-Dist: textual==1.0.0
Requires-Dist: tqdm~=4.66.4
Requires-Dist: uvloop~=0.21.0; sys_platform == 'linux' or sys_platform == 'linux2'
Requires-Dist: win32-setctime~=1.1.0
Requires-Dist: xxhash~=3.4.1
Provides-Extra: dev
Requires-Dist: autopep8~=2.0.2; extra == 'dev'
Requires-Dist: pyinstaller; extra == 'dev'
Provides-Extra: docs
Requires-Dist: sphinx-argparse~=0.5.2; extra == 'docs'
Provides-Extra: ffmpeg
Requires-Dist: pyffmpeg==2.4.2.20; extra == 'ffmpeg'
Provides-Extra: test
Requires-Dist: coverage~=7.4.3; extra == 'test'
Requires-Dist: pytest-cov~=4.1.0; extra == 'test'
Requires-Dist: pytest-mock~=3.12.0; extra == 'test'
Requires-Dist: pytest~=7.3.1; extra == 'test'
Requires-Dist: random-emoji~=1.0.15; extra == 'test'
Requires-Dist: random-unicode-emoji~=2.8; extra == 'test'
